cuteroll
