Metadata-Version: 2.1
Name: cuteroll
Version: 1.0.1
Summary: Download shows from crunchyroll
Home-page: https://github.com/insidewhy/cuteroll
Author: insidewhy
License: MIT
Platform: UNKNOWN
License-File: LICENSE
